digicloud/__init__.py
digicloud/__main__.py
digicloud/documentations.py
digicloud/error_handlers.py
digicloud/formatter.py
digicloud/main.py
digicloud/managers.py
digicloud/middlewares.py
digicloud/schemas.py
digicloud/sentry.py
digicloud/utils.py
digicloud/cli/__init__.py
digicloud/cli/app.py
digicloud/cli/formatters.py
digicloud/cli/parseractions.py
digicloud/commands/__init__.py
digicloud/commands/access.py
digicloud/commands/account.py
digicloud/commands/base.py
digicloud/commands/cluster.py
digicloud/commands/config.py
digicloud/commands/database.py
digicloud/commands/edge.py
digicloud/commands/explain.py
digicloud/commands/ike.py
digicloud/commands/image.py
digicloud/commands/instance.py
digicloud/commands/instance_operations.py
digicloud/commands/instance_type.py
digicloud/commands/ipsec.py
digicloud/commands/load_balancer.py
digicloud/commands/namespace.py
digicloud/commands/network.py
digicloud/commands/oss.py
digicloud/commands/quota.py
digicloud/commands/region.py
digicloud/commands/router.py
digicloud/commands/security.py
digicloud/commands/server_group.py
digicloud/commands/snapshot.py
digicloud/commands/ssh_key.py
digicloud/commands/subnet.py
digicloud/commands/volume.py
digicloud/commands/vpn.py
digicloud/documentations/cluster.md
digicloud/documentations/database.md
digicloud/documentations/digicloud.md
digicloud/documentations/edge.md
digicloud/documentations/firewall.md
digicloud/documentations/ike.md
digicloud/documentations/instance.md
digicloud/documentations/ipsec.md
digicloud/documentations/loadbalancer.md
digicloud/documentations/login_required.md
digicloud/documentations/namespace.md
digicloud/documentations/network.md
digicloud/documentations/oss.md
digicloud/documentations/public_ip.md
digicloud/documentations/region.md
digicloud/documentations/router.md
digicloud/documentations/snapshot.md
digicloud/documentations/ssh-key.md
digicloud/documentations/subnet.md
digicloud/documentations/volume.md
digicloud/documentations/vpn.md
digicloud-2.5.24.dist-info/LICENSE
digicloud-2.5.24.dist-info/METADATA
digicloud-2.5.24.dist-info/WHEEL
digicloud-2.5.24.dist-info/entry_points.txt
digicloud-2.5.24.dist-info/top_level.txt
digicloud-2.5.24.dist-info/RECORD
