Metadata-Version: 2.1
Name: digicloud
Version: 2.5.24
Summary: DigiCloud CLI
Home-page: https://digicloud.ir
Author: Arash Shams
Author-email: a.shams@digikala.com
License: UNKNOWN
Platform: Any
Classifier: Development Status :: 4 - Beta
Classifier: License :: OSI Approved :: Apache Software License
Classifier: Programming Language :: Python
Classifier: Programming Language :: Python :: 3
Classifier: Programming Language :: Python :: 3.5
Classifier: Programming Language :: Python :: 3.6
Classifier: Programming Language :: Python :: 3.7
Classifier: Programming Language :: Python :: 3.8
Classifier: Programming Language :: Python :: 3.9
Classifier: Intended Audience :: Developers
Classifier: Environment :: Console
License-File: LICENSE
Requires-Dist: cliff
Requires-Dist: rich
Requires-Dist: requests
Requires-Dist: marshmallow
Requires-Dist: setuptools
Requires-Dist: tzlocal
Requires-Dist: pytz
Requires-Dist: sentry-sdk
Requires-Dist: tabulate
Provides-Extra: dev
Requires-Dist: pytest==6.1.0; extra == "dev"
